test_git/c.py
qwest_git-0.1.19.dist-info/LICENSE
qwest_git-0.1.19.dist-info/METADATA
qwest_git-0.1.19.dist-info/WHEEL
qwest_git-0.1.19.dist-info/RECORD
